{
  "categories": [
    {
      "name": "Ubrania",
      "items": [
        "skarpetki",
        "majtki",
        "koszulki",
        "spodnie",
        "spodenki",
        "dresy",
        "bluza",
        "koszula",
        "sweter",
        "rękawiczki",
        "szalik",
        "czapka",
        "buty",
        "klapki",
        "stanik",
        "bielizna termiczna",
        "pasek",
        "kapelusz",
        "kurtka"
      ]
    },
    {
      "name": "Toaleta",
      "items": [
        "szczotka do włosów",
        "szczoteczka do zębów",
        "pasta do zębów",
        "mydło ",
        "szampon",
        "dezodorant",
        "perfumy",
        "ręcznik",
        "kosmetyki",
        "pilnik i cążki do paznokci",
        "papier toaletowy",
        "chusteczki",
        "gumka do włosów",
        "emulsja do opalania",
        "płyn do higieny intymnej",
        "wkładka na palce ",
        "sprzęt do naprawy ucha ",
        "nitka dentystyczna",
        "pasta do butów"
      ]
    },
    {
      "name": "Dokumenty",
      "items": [
        "dowód",
        "paszport",
        "prawo jazdy",
        "ubezpieczenie",
        "EKUZ",
        "revolut",
        "pieniądze",
        "euro"
      ]
    },
    {
      "name": "Elektronika",
      "items": [
        "aparat fotograficzny",
        "zegarek",
        "ładowarka",
        "tablet ",
        "laptop",
        "ładowarka do laptopa",
        "kabel USB",
        "walkie-talkie ",
        "power bank"
      ]
    },
    {
      "name": "Biwak",
      "items": [
        "nóż",
        "łyżka",
        "widelec",
        "kubek",
        "menażka",
        "garnek",
        "butla",
        "latarka",
        "śpiwór",
        "karimata",
        "namiot",
        "mapy ",
        "koc",
        "poduszka",
        "prześcieradło",
        "linka",
        "bidon",
        "przybory do szycia",
        "długopis",
        "notes",
        "płaszcz przeciwdeszczowy",
        "piersiówka",
        "teleskop"
      ]
    },
    {
      "name": "Rower",
      "items": [
        "narzędzia rowerowe",
        "dętki",
        "rękawiczki rowerowe",
        "kask",
        "zabezpieczenie rowerowe",
        "okulary",
        "neopren na buty"
      ]
    },
    {
      "name": "Narty",
      "items": [
        "spodnie narciarskie ",
        "buty narciarskie",
        "kijki",
        "narty",
        "gogle"
      ]
    },
    {
      "name": "Sport",
      "items": [
        "okularki pływackie ",
        "dmuchane zabawki ",
        "piłka ⚽ ",
        "buty do biegania",
        "spodenki do biegania",
        "koszulka do biegania",
        "spodnie żeglarskie",
        "kurtka nieprzemakalna",
        "stuptuty",
        "kostium kąpielowy",
        "worek wodoodporny",
        "sup",
        "wiosło"
      ]
    },
    {
      "name": "Samochód",
      "items": [
        "kamizelka odblaskowa ",
        "lina holownicza ",
        "łańcuchy "
      ]
    },
    {
      "name": "Apteczka",
      "items": [
        "lekarstwa",
        "plastry",
        "kompresy",
        "szczepionka",
        "telfexo"
      ]
    },
    {
      "name": "Muzyka",
      "items": [
        "gitara",
        "ukulele",
        "śpiewniki",
        "stroik",
        "kostki",
        "kapodaster"
      ]
    },
    {
      "name": "Inne",
      "items": [
        "klucze",
        "jedzenie",
        "whiskey ",
        "piwo",
        "ostrzałka"
      ]
    }
  ]
}